<?xml version="1.0" encoding="UTF-8"?>
<beans xmlns="http://www.springframework.org/schema/beans"
       xmlns:xsi="http://www.w3.org/2001/XMLSchema-instance"
       xmlns:context="http://www.springframework.org/schema/context" xmlns:tx="http://www.springframework.org/schema/tx"
       xmlns:aop="http://www.springframework.org/schema/aop"
       xsi:schemaLocation="http://www.springframework.org/schema/beans
       http://www.springframework.org/schema/beans/spring-beans.xsd http://www.springframework.org/schema/context https://www.springframework.org/schema/context/spring-context.xsd http://www.springframework.org/schema/tx http://www.springframework.org/schema/tx/spring-tx.xsd http://www.springframework.org/schema/aop https://www.springframework.org/schema/aop/spring-aop.xsd">
    <context:property-placeholder location="classpath:jdbc.properties"/>
    <context:component-scan base-package="org.example"/>
    <bean id="druidDataSource" class="com.alibaba.druid.pool.DruidDataSource">
        <property name="driverClassName" value="${jdbc.driver}"/>
        <property name="url" value="${jdbc.url}"/>
        <property name="username" value="${jdbc.username}"/>
        <property name="password" value="${jdbc.password}"/>
    </bean>
    <bean id="jdbcTemplate" class="org.springframework.jdbc.core.JdbcTemplate">
        <property name="dataSource" ref="druidDataSource"/>
    </bean>
    <!--配置事务管理器(数据源事务管理器)-->
    <bean id="transactionManager" class="org.springframework.jdbc.datasource.DataSourceTransactionManager">
        <property name="dataSource" ref="druidDataSource"/>
    </bean>
    <!--配置事务通知-->
    <tx:advice id="tx">
        <tx:attributes>
            <tx:method name="buyBook" read-only="false" isolation="DEFAULT" propagation="REQUIRED"/>
            <tx:method name="checkout" read-only="false" isolation="DEFAULT" propagation="REQUIRED"/>
            <!-- name属性：指定方法名，可以使用星号代表多个字符 -->
            <tx:method name="get*" read-only="true"/>
            <tx:method name="update*" read-only="false" rollback-for="java.lang.Exception" propagation="REQUIRES_NEW"/>
            <tx:method name="*"/>
        </tx:attributes>
    </tx:advice>
    <aop:config>
        <aop:advisor advice-ref="tx" pointcut="execution(* org.example.service.Impl.*.*(..))"/>
    </aop:config>
</beans>